{
  "id": "af915516-318a-4a8d-8789-43c8e0c8e076",
  "prevId": "c310443c-957e-4b6e-b327-bae42bd54659",
  "version": "7",
  "dialect": "postgresql",
  "tables": {
    "public.model_requets": {
      "name": "model_requets",
      "schema": "",
      "columns": {
        "request_id": {
          "name": "request_id",
          "type": "uuid",
          "primaryKey": true,
          "notNull": true,
          "default": "gen_random_uuid()"
        },
        "name": {
          "name": "name",
          "type": "text",
          "primaryKey": false,
          "notNull": true
        },
        "model_name": {
          "name": "model_name",
          "type": "text",
          "primaryKey": false,
          "notNull": true
        },
        "provider": {
          "name": "provider",
          "type": "text",
          "primaryKey": false,
          "notNull": true
        },
        "urgency": {
          "name": "urgency",
          "type": "urgency_status",
          "typeSchema": "public",
          "primaryKey": false,
          "notNull": false,
          "default": "'normal'"
        },
        "details": {
          "name": "details",
          "type": "text",
          "primaryKey": false,
          "notNull": true
        },
        "created_at": {
          "name": "created_at",
          "type": "timestamp with time zone",
          "primaryKey": false,
          "notNull": true,
          "default": "now()"
        },
        "updated_at": {
          "name": "updated_at",
          "type": "timestamp with time zone",
          "primaryKey": false,
          "notNull": true
        }
      },
      "indexes": {},
      "foreignKeys": {},
      "compositePrimaryKeys": {},
      "uniqueConstraints": {},
      "policies": {},
      "checkConstraints": {},
      "isRLSEnabled": false
    },
    "public.users": {
      "name": "users",
      "schema": "",
      "columns": {
        "user_id": {
          "name": "user_id",
          "type": "uuid",
          "primaryKey": true,
          "notNull": true,
          "default": "gen_random_uuid()"
        },
        "ip": {
          "name": "ip",
          "type": "text",
          "primaryKey": false,
          "notNull": true
        },
        "user_agent": {
          "name": "user_agent",
          "type": "text",
          "primaryKey": false,
          "notNull": true
        },
        "prompt_history": {
          "name": "prompt_history",
          "type": "text[]",
          "primaryKey": false,
          "notNull": false,
          "default": "'{}'"
        },
        "created_at": {
          "name": "created_at",
          "type": "timestamp with time zone",
          "primaryKey": false,
          "notNull": true,
          "default": "now()"
        },
        "updated_at": {
          "name": "updated_at",
          "type": "timestamp with time zone",
          "primaryKey": false,
          "notNull": true
        }
      },
      "indexes": {},
      "foreignKeys": {},
      "compositePrimaryKeys": {},
      "uniqueConstraints": {},
      "policies": {},
      "checkConstraints": {},
      "isRLSEnabled": false
    }
  },
  "enums": {
    "public.urgency_status": {
      "name": "urgency_status",
      "schema": "public",
      "values": [
        "normal",
        "high",
        "critical"
      ]
    }
  },
  "schemas": {},
  "sequences": {},
  "roles": {},
  "policies": {},
  "views": {},
  "_meta": {
    "columns": {},
    "schemas": {},
    "tables": {}
  }
}